activity/__init__.py
activity/admin.py
activity/api.py
activity/apps.py
activity/client.py
activity/constants.py
activity/consumer.py
activity/factories.py
activity/models.py
activity/services.py
activity/views.py
activity/migrations/0001_initial.py
activity/migrations/__init__.py
p1_activity-0.3.2.dist-info/LICENSE
p1_activity-0.3.2.dist-info/METADATA
p1_activity-0.3.2.dist-info/WHEEL
p1_activity-0.3.2.dist-info/top_level.txt
p1_activity-0.3.2.dist-info/RECORD
