Metadata-Version: 2.1
Name: p1-activity
Version: 0.3.2
Summary: A simple consumer Django app for Activity Service.
Author: Yonas & Wisnu
Author-email: engineering@dekoruma.com
License: MIT
Classifier: Environment :: Web Environment
Classifier: Framework :: Django
Classifier: Framework :: Django :: 1.11
Classifier: Intended Audience :: Developers
Classifier: Operating System :: OS Independent
Classifier: Programming Language :: Python
Classifier: Programming Language :: Python :: 2.7
Classifier: Topic :: Internet :: WWW/HTTP
Classifier: Topic :: Internet :: WWW/HTTP :: Dynamic Content
License-File: LICENSE
Requires-Dist: p1-queue >=0.4.2
Requires-Dist: factory-boy >=3.0.0
